odoo/addons/product_configurator_purchase/README.rst
odoo/addons/product_configurator_purchase/__init__.py
odoo/addons/product_configurator_purchase/__manifest__.py
odoo/addons/product_configurator_purchase/data/menu_product.xml
odoo/addons/product_configurator_purchase/demo/product_template.xml
odoo/addons/product_configurator_purchase/i18n/product_configurator_purchase.pot
odoo/addons/product_configurator_purchase/models/__init__.py
odoo/addons/product_configurator_purchase/models/purchase.py
odoo/addons/product_configurator_purchase/readme/DESCRIPTION.rst
odoo/addons/product_configurator_purchase/security/ir.model.access.csv
odoo/addons/product_configurator_purchase/static/description/icon.png
odoo/addons/product_configurator_purchase/static/description/index.html
odoo/addons/product_configurator_purchase/tests/__init__.py
odoo/addons/product_configurator_purchase/tests/test_purchase.py
odoo/addons/product_configurator_purchase/views/purchase_view.xml
odoo/addons/product_configurator_purchase/wizard/__init__.py
odoo/addons/product_configurator_purchase/wizard/product_configurator.py
odoo14_addon_product_configurator_purchase-14.0.1.1.0.dist-info/METADATA
odoo14_addon_product_configurator_purchase-14.0.1.1.0.dist-info/WHEEL
odoo14_addon_product_configurator_purchase-14.0.1.1.0.dist-info/top_level.txt
odoo14_addon_product_configurator_purchase-14.0.1.1.0.dist-info/RECORD
